rtl/voting_unit.v
/*
 * Onyx V2 — Voting Unit (FDE)
 * =============================
 * Firing Direction Encoding voting.
 * N_INPUTS مذبذبات، كل واحد يعطي firing_dir.
 * القرار: majority vote — pos vs neg.
 *
 * كسر التعادل: مجموع fire_counts.
 */

module voting_unit #(
    parameter N_INPUTS = 6,
    parameter COUNT_WIDTH = 32
)(
    input  wire [N_INPUTS-1:0]             firing_dir,   // 1=pos, 0=neg
    input  wire [N_INPUTS*COUNT_WIDTH-1:0] fire_counts,  // متسلسلة
    output reg                             decision,     // 1=موجب, 0=سالب
    output reg                             valid         // قرار صحيح
);

    integer i;
    reg [31:0] pos_votes;
    reg [31:0] neg_votes;
    reg [COUNT_WIDTH-1:0] pos_fires;
    reg [COUNT_WIDTH-1:0] neg_fires;

    always @(*) begin
        pos_votes = 0;
        neg_votes = 0;
        pos_fires = 0;
        neg_fires = 0;

        for (i = 0; i < N_INPUTS; i = i + 1) begin
            if (firing_dir[i]) begin
                pos_votes = pos_votes + 1;
                pos_fires = pos_fires + fire_counts[i*COUNT_WIDTH +: COUNT_WIDTH];
            end else begin
                neg_votes = neg_votes + 1;
                neg_fires = neg_fires + fire_counts[i*COUNT_WIDTH +: COUNT_WIDTH];
            end
        end

        if (pos_votes > neg_votes) begin
            decision = 1;
            valid = 1;
        end else if (neg_votes > pos_votes) begin
            decision = 0;
            valid = 1;
        end else begin
            // Tiebreak: مجموع الإطلاقات
            decision = (pos_fires >= neg_fires) ? 1 : 0;
            valid = 1;
        end
    end

endmodule

rtl/nco_oscillator.v
/*
 * Onyx V2 — NCO Oscillator مع LFSR مدمج
 * ========================================
 * كل مذبذب له LFSR الخاص به (seed مختلف).
 * 32-bit signed NCO + مقارنات عتبة + FDE
 */

module nco_oscillator #(
    parameter ACC_WIDTH = 32,
    parameter THRESHOLD = 32'h40000000,
    parameter OFFSET    = 32'h20000000,
    parameter LFSR_SEED = 32'hACE1_42BD
)(
    input  wire                 clk,
    input  wire                 rst_n,
    input  wire                 enable,
    input  wire signed [ACC_WIDTH-1:0] f_word,
    output reg                  fire_pos,
    output reg                  fire_neg,
    output reg  [ACC_WIDTH-1:0] fire_count,
    output reg                  firing_dir
);

    reg signed [ACC_WIDTH-1:0] acc;
    reg [ACC_WIDTH-1:0]        lfsr_state;

    // LFSR polynomial: x^32 + x^22 + x^2 + x^1 + 1
    wire feedback = lfsr_state[0];
    wire [ACC_WIDTH-1:0] next_lfsr = {lfsr_state[ACC_WIDTH-2:0], 1'b0};
    wire signed [ACC_WIDTH-1:0] noise =
        {lfsr_state[7:0], lfsr_state[15:8], lfsr_state[23:16], lfsr_state[31:24]} / 2;

    always @(posedge clk or negedge rst_n) begin
        if (!rst_n) begin
            acc        <= 0;
            fire_pos   <= 0;
            fire_neg   <= 0;
            fire_count <= 0;
            firing_dir <= 0;
            lfsr_state <= LFSR_SEED;
        end else if (enable) begin
            // LFSR step
            if (feedback)
                lfsr_state <= next_lfsr ^ 32'hB4BCD35C;
            else
                lfsr_state <= next_lfsr;

            // NCO accumulate: acc += f_word + noise
            acc <= acc + f_word + noise;

            // Threshold comparison
            if (acc > $signed(THRESHOLD)) begin
                fire_pos   <= 1;
                fire_neg   <= 0;
                firing_dir <= 1;
                acc        <= acc - $signed(OFFSET);
                fire_count <= fire_count + 1;
            end else if (acc < -$signed(THRESHOLD)) begin
                fire_neg   <= 1;
                fire_pos   <= 0;
                firing_dir <= 0;
                acc        <= acc + $signed(OFFSET);
                fire_count <= fire_count + 1;
            end else begin
                fire_pos <= 0;
                fire_neg <= 0;
            end
        end
    end

endmodule

rtl/onyx_core.v
/*
 * Onyx V2 — Core (Top Level)
 * ============================
 * خزان مذبذبات NCO + ضوضاء LFSR + تصويت FDE
 *
 * N_OSC = 6 مذبذبات
 * N_WINDOW = 2 دورات ساعة للتصنيف
 * N_SAMPLES = 50 تصنيف
 *
 * التحكم:
 *   start → يصنف عينة واحدة ← done = 1 مع decision
 *   يتم تغذية signal_value عبر واجهة 32-bit
 */

module onyx_core #(
    parameter N_OSC = 6,
    parameter ACC_WIDTH = 32,
    parameter THRESHOLD = 32'h40000000,
    parameter OFFSET    = 32'h20000000,
    parameter N_WINDOW  = 2
)(
    input  wire                 clk,
    input  wire                 rst_n,
    input  wire                 start,           // بدء تصنيف عينة
    input  wire signed [31:0]   signal_value,    // الإشارة الداخلة (signed)
    output reg                  done,             // انتهى التصنيف
    output reg                  decision,         // 1=موجب, 0=سالب
    output reg  [15:0]          total_fires,      // إجمالي الإطلاقات
    output reg  [31:0]          debug_state       // للحالة الداخلية (Debug)
);

    // ========== FSM States ==========
    localparam IDLE    = 2'b00;
    localparam RUN     = 2'b01;
    localparam VOTE    = 2'b10;
    localparam DONE_ST = 2'b11;

    reg [1:0] state;
    reg [7:0] step_counter;
    reg [7:0] sample_counter;

    // ========== NCO Oscillators x6 ==========
    wire [N_OSC-1:0]             osc_fire_pos;
    wire [N_OSC-1:0]             osc_fire_neg;
    wire [N_OSC-1:0]             osc_firing_dir;
    wire [N_OSC*ACC_WIDTH-1:0]   osc_fire_counts;

    // توليد المذبذبات (كل واحد مع LFSR مدمج و seed مستقل)
    genvar i;
    generate
        for (i = 0; i < N_OSC; i = i + 1) begin : osc_bank
            // عتبات مختلفة لكل مذبذب (0.8×TH إلى 1.2×TH)
            localparam [31:0] OSC_TH = THRESHOLD +
                (THRESHOLD * ((i * 40) / (N_OSC * 100))) - (THRESHOLD / 5);
            // Seeds مختلفة لكل مذبذب
            localparam [31:0] OSC_SEED = 32'hACE1_42BD + (i * 32'h1000_0000);

            nco_oscillator #(
                .ACC_WIDTH(ACC_WIDTH),
                .THRESHOLD(OSC_TH),
                .OFFSET(OFFSET),
                .LFSR_SEED(OSC_SEED)
            ) osc (
                .clk(clk),
                .rst_n(rst_n),
                .enable((state == RUN)),
                .f_word(signal_value),
                .fire_pos(osc_fire_pos[i]),
                .fire_neg(osc_fire_neg[i]),
                .fire_count(osc_fire_counts[i*ACC_WIDTH +: ACC_WIDTH]),
                .firing_dir(osc_firing_dir[i])
            );
        end
    endgenerate

    // ========== Voting Unit ==========
    wire vote_decision;
    wire vote_valid;

    voting_unit #(
        .N_INPUTS(N_OSC),
        .COUNT_WIDTH(ACC_WIDTH)
    ) voter (
        .firing_dir(osc_firing_dir),
        .fire_counts(osc_fire_counts),
        .decision(vote_decision),
        .valid(vote_valid)
    );

    // ========== FSM ==========
    always @(posedge clk or negedge rst_n) begin
        if (!rst_n) begin
            state        <= IDLE;
            done         <= 0;
            decision     <= 0;
            total_fires  <= 0;
            step_counter <= 0;
            sample_counter <= 0;
            debug_state  <= 0;
        end else begin
            case (state)
                IDLE: begin
                    done <= 0;
                    if (start) begin
                        state <= RUN;
                        step_counter <= 0;
                    end
                    debug_state <= 32'h0000_0001;
                end

                RUN: begin
                    step_counter <= step_counter + 1;
                    debug_state <= {24'h0000_01, step_counter};

                    if (step_counter >= N_WINDOW - 1) begin
                        state <= VOTE;
                    end
                end

                VOTE: begin
                    // Collect total fires
                    total_fires <=
                        osc_fire_counts[0*ACC_WIDTH +: ACC_WIDTH] +
                        osc_fire_counts[1*ACC_WIDTH +: ACC_WIDTH] +
                        osc_fire_counts[2*ACC_WIDTH +: ACC_WIDTH] +
                        osc_fire_counts[3*ACC_WIDTH +: ACC_WIDTH] +
                        osc_fire_counts[4*ACC_WIDTH +: ACC_WIDTH] +
                        osc_fire_counts[5*ACC_WIDTH +: ACC_WIDTH];
                    state <= DONE_ST;
                    debug_state <= 32'h0000_0003;
                end

                DONE_ST: begin
                    decision <= vote_decision;
                    done <= 1;
                    debug_state <= {16'h0000, 8'hFF, vote_decision, 7'b0, 1'b1};
                    if (!start) begin
                        state <= IDLE;
                    end
                end
            endcase
        end
    end

endmodule

tb/tb_onyx_core_v2.v
/*
 * Onyx V2 — Testbench v2 مع N_WINDOW=5 وأكثر تفصيلاً
 * =====================================================
 */
`timescale 1ns / 1ps

module tb_onyx_core_v2;

    reg clk, rst_n, start;
    reg signed [31:0] signal_value;
    wire done, decision;
    wire [15:0] total_fires;
    wire [31:0] debug_state;

    onyx_core #(.N_OSC(6), .N_WINDOW(5)) dut (
        .clk(clk), .rst_n(rst_n), .start(start),
        .signal_value(signal_value),
        .done(done), .decision(decision),
        .total_fires(total_fires), .debug_state(debug_state)
    );

    always #5 clk = ~clk;

    reg [31:0] sig_pos = 32'h2000_0000;  // +0.5 * TH
    reg [31:0] sig_neg = -32'h2000_0000; // -0.5 * TH

    integer i, correct;
    reg d;

    initial begin
        clk = 0; rst_n = 0; start = 0;
        #15 rst_n = 1;
        #10;

        $display("Onyx V2 — Debug: Testing single samples");
        $display("");

        // Test positive signal
        signal_value = sig_pos;
        start = 1; #10; start = 0;
        @(posedge done); #1;
        $display("POS signal (%0d): decision=%0d, fires=%0d, dbg=%h",
            sig_pos, decision, total_fires, debug_state);

        // Test negative signal
        signal_value = sig_neg;
        #20;
        start = 1; #10; start = 0;
        @(posedge done); #1;
        $display("NEG signal (%0d): decision=%0d, fires=%0d, dbg=%h",
            sig_neg, decision, total_fires, debug_state);

        // Full classification run
        $display("");
        $display("--- Full test: 25 POS + 25 NEG ---");
        correct = 0;
        for (i = 0; i < 25; i = i + 1) begin
            signal_value = sig_pos;
            start = 1; #10; start = 0;
            @(posedge done); #1;
            d = decision;
            if (d == 1) correct = correct + 1;
            else $display("  POS sample %0d FAILED (decision=%0d)", i, d);
            #10;
        end
        for (i = 0; i < 25; i = i + 1) begin
            signal_value = sig_neg;
            start = 1; #10; start = 0;
            @(posedge done); #1;
            d = decision;
            if (d == 0) correct = correct + 1;
            else $display("  NEG sample %0d FAILED (decision=%0d)", i, d);
            #10;
        end

        $display("");
        $display("Final: %0d/50 correct (%0.1f%%)",
            correct, correct * 2.0);
        $finish;
    end

    initial begin
        $dumpfile("tb_onyx_v2.vcd");
        $dumpvars(0, tb_onyx_core_v2);
    end

endmodule

tb_onyx_v2.vcd
$date
	Wed Apr 29 01:13:18 2026
$end
$version
	Icarus Verilog
$end
$timescale
	1ps
$end
$scope module tb_onyx_core_v2 $end
$var wire 16 ! total_fires [15:0] $end
$var wire 1 " done $end
$var wire 1 # decision $end
$var wire 32 $ debug_state [31:0] $end
$var reg 1 % clk $end
$var reg 1 & d $end
$var reg 1 ' rst_n $end
$var reg 32 ( sig_neg [31:0] $end
$var reg 32 ) sig_pos [31:0] $end
$var reg 32 * signal_value [31:0] $end
$var reg 1 + start $end
$var integer 32 , correct [31:0] $end
$var integer 32 - i [31:0] $end
$scope module dut $end
$var wire 1 % clk $end
$var wire 1 ' rst_n $end
$var wire 32 . signal_value [31:0] $end
$var wire 1 + start $end
$var wire 1 / vote_valid $end
$var wire 1 0 vote_decision $end
$var wire 6 1 osc_firing_dir [5:0] $end
$var wire 6 2 osc_fire_pos [5:0] $end
$var wire 6 3 osc_fire_neg [5:0] $end
$var wire 192 4 osc_fire_counts [191:0] $end
$var parameter 32 5 ACC_WIDTH $end
$var parameter 2 6 DONE_ST $end
$var parameter 2 7 IDLE $end
$var parameter 32 8 N_OSC $end
$var parameter 32 9 N_WINDOW $end
$var parameter 32 : OFFSET $end
$var parameter 2 ; RUN $end
$var parameter 32 < THRESHOLD $end
$var parameter 2 = VOTE $end
$var reg 32 > debug_state [31:0] $end
$var reg 1 # decision $end
$var reg 1 " done $end
$var reg 8 ? sample_counter [7:0] $end
$var reg 2 @ state [1:0] $end
$var reg 8 A step_counter [7:0] $end
$var reg 16 B total_fires [15:0] $end
$scope begin osc_bank[0] $end
$var parameter 32 C OSC_SEED $end
$var parameter 32 D OSC_TH $end
$var parameter 2 E i $end
$scope module osc $end
$var wire 1 % clk $end
$var wire 1 F enable $end
$var wire 32 G f_word [31:0] $end
$var wire 1 ' rst_n $end
$var wire 32 H noise [31:0] $end
$var wire 32 I next_lfsr [31:0] $end
$var wire 1 J feedback $end
$var parameter 32 K ACC_WIDTH $end
$var parameter 32 L LFSR_SEED $end
$var parameter 32 M OFFSET $end
$var parameter 32 N THRESHOLD $end
$var reg 32 O acc [31:0] $end
$var reg 32 P fire_count [31:0] $end
$var reg 1 Q fire_neg $end
$var reg 1 R fire_pos $end
$var reg 1 S firing_dir $end
$var reg 32 T lfsr_state [31:0] $end
$upscope $end
$upscope $end
$scope begin osc_bank[1] $end
$var parameter 32 U OSC_SEED $end
$var parameter 32 V OSC_TH $end
$var parameter 2 W i $end
$scope module osc $end
$var wire 1 % clk $end
$var wire 1 X enable $end
$var wire 32 Y f_word [31:0] $end
$var wire 1 ' rst_n $end
$var wire 32 Z noise [31:0] $end
$var wire 32 [ next_lfsr [31:0] $end
$var wire 1 \ feedback $end
$var parameter 32 ] ACC_WIDTH $end
$var parameter 32 ^ LFSR_SEED $end
$var parameter 32 _ OFFSET $end
$var parameter 32 ` THRESHOLD $end
$var reg 32 a acc [31:0] $end
$var reg 32 b fire_count [31:0] $end
$var reg 1 c fire_neg $end
$var reg 1 d fire_pos $end
$var reg 1 e firing_dir $end
$var reg 32 f lfsr_state [31:0] $end
$upscope $end
$upscope $end
$scope begin osc_bank[2] $end
$var parameter 32 g OSC_SEED $end
$var parameter 32 h OSC_TH $end
$var parameter 3 i i $end
$scope module osc $end
$var wire 1 % clk $end
$var wire 1 j enable $end
$var wire 32 k f_word [31:0] $end
$var wire 1 ' rst_n $end
$var wire 32 l noise [31:0] $end
$var wire 32 m next_lfsr [31:0] $end
$var wire 1 n feedback $end
$var parameter 32 o ACC_WIDTH $end
$var parameter 32 p LFSR_SEED $end
$var parameter 32 q OFFSET $end
$var parameter 32 r THRESHOLD $end
$var reg 32 s acc [31:0] $end
$var reg 32 t fire_count [31:0] $end
$var reg 1 u fire_neg $end
$var reg 1 v fire_pos $end
$var reg 1 w firing_dir $end
$var reg 32 x lfsr_state [31:0] $end
$upscope $end
$upscope $end
$scope begin osc_bank[3] $end
$var parameter 32 y OSC_SEED $end
$var parameter 32 z OSC_TH $end
$var parameter 3 { i $end
$scope module osc $end
$var wire 1 % clk $end
$var wire 1 | enable $end
$var wire 32 } f_word [31:0] $end
$var wire 1 ' rst_n $end
$var wire 32 ~ noise [31:0] $end
$var wire 32 !" next_lfsr [31:0] $end
$var wire 1 "" feedback $end
$var parameter 32 #" ACC_WIDTH $end
$var parameter 32 $" LFSR_SEED $end
$var parameter 32 %" OFFSET $end
$var parameter 32 &" THRESHOLD $end
$var reg 32 '" acc [31:0] $end
$var reg 32 (" fire_count [31:0] $end
$var reg 1 )" fire_neg $end
$var reg 1 *" fire_pos $end
$var reg 1 +" firing_dir $end
$var reg 32 ," lfsr_state [31:0] $end
$upscope $end
$upscope $end
$scope begin osc_bank[4] $end
$var parameter 32 -" OSC_SEED $end
$var parameter 32 ." OSC_TH $end
$var parameter 4 /" i $end
$scope module osc $end
$var wire 1 % clk $end
$var wire 1 0" enable $end
$var wire 32 1" f_word [31:0] $end
$var wire 1 ' rst_n $end
$var wire 32 2" noise [31:0] $end
$var wire 32 3" next_lfsr [31:0] $end
$var wire 1 4" feedback $end
$var parameter 32 5" ACC_WIDTH $end
$var parameter 32 6" LFSR_SEED $end
$var parameter 32 7" OFFSET $end
$var parameter 32 8" THRESHOLD $end
$var reg 32 9" acc [31:0] $end
$var reg 32 :" fire_count [31:0] $end
$var reg 1 ;" fire_neg $end
$var reg 1 <" fire_pos $end
$var reg 1 =" firing_dir $end
$var reg 32 >" lfsr_state [31:0] $end
$upscope $end
$upscope $end
$scope begin osc_bank[5] $end
$var parameter 32 ?" OSC_SEED $end
$var parameter 32 @" OSC_TH $end
$var parameter 4 A" i $end
$scope module osc $end
$var wire 1 % clk $end
$var wire 1 B" enable $end
$var wire 32 C" f_word [31:0] $end
$var wire 1 ' rst_n $end
$var wire 32 D" noise [31:0] $end
$var wire 32 E" next_lfsr [31:0] $end
$var wire 1 F" feedback $end
$var parameter 32 G" ACC_WIDTH $end
$var parameter 32 H" LFSR_SEED $end
$var parameter 32 I" OFFSET $end
$var parameter 32 J" THRESHOLD $end
$var reg 32 K" acc [31:0] $end
$var reg 32 L" fire_count [31:0] $end
$var reg 1 M" fire_neg $end
$var reg 1 N" fire_pos $end
$var reg 1 O" firing_dir $end
$var reg 32 P" lfsr_state [31:0] $end
$upscope $end
$upscope $end
$scope module voter $end
$var wire 192 Q" fire_counts [191:0] $end
$var wire 6 R" firing_dir [5:0] $end
$var parameter 32 S" COUNT_WIDTH $end
$var parameter 32 T" N_INPUTS $end
$var reg 1 0 decision $end
$var reg 32 U" neg_fires [31:0] $end
$var reg 32 V" neg_votes [31:0] $end
$var reg 32 W" pos_fires [31:0] $end
$var reg 32 X" pos_votes [31:0] $end
$var reg 1 / valid $end
$var integer 32 Y" i [31:0] $end
$upscope $end
$upscope $end
$upscope $end
$enddefinitions $end
$comment Show the parameter values. $end
$dumpall
b110 T"
b100000 S"
b110011001100110011001100110100 J"
b100000000000000000000000000000 I"
b11111100111000010100001010111101 H"
b100000 G"
b101 A"
b110011001100110011001100110100 @"
b11111100111000010100001010111101 ?"
b110011001100110011001100110100 8"
b100000000000000000000000000000 7"
b11101100111000010100001010111101 6"
b100000 5"
b100 /"
b110011001100110011001100110100 ."
b11101100111000010100001010111101 -"
b110011001100110011001100110100 &"
b100000000000000000000000000000 %"
b11011100111000010100001010111101 $"
b100000 #"
b11 {
b110011001100110011001100110100 z
b11011100111000010100001010111101 y
b110011001100110011001100110100 r
b100000000000000000000000000000 q
b11001100111000010100001010111101 p
b100000 o
b10 i
b110011001100110011001100110100 h
b11001100111000010100001010111101 g
b110011001100110011001100110100 `
b100000000000000000000000000000 _
b10111100111000010100001010111101 ^
b100000 ]
b1 W
b110011001100110011001100110100 V
b10111100111000010100001010111101 U
b110011001100110011001100110100 N
b100000000000000000000000000000 M
b10101100111000010100001010111101 L
b100000 K
b0 E
b110011001100110011001100110100 D
b10101100111000010100001010111101 C
b10 =
b1000000000000000000000000000000 <
b1 ;
b100000000000000000000000000000 :
b101 9
b110 8
b0 7
b11 6
b100000 5
$end
#0
$dumpvars
b110 Y"
b0 X"
b0 W"
b110 V"
b0 U"
b0 R"
b0 Q"
b11111100111000010100001010111101 P"
0O"
0N"
0M"
b0 L"
b0 K"
1F"
b11111001110000101000010101111010 E"
b1011110101000010111000011111110 D"
bx C"
0B"
b11101100111000010100001010111101 >"
0="
0<"
0;"
b0 :"
b0 9"
14"
b11011001110000101000010101111010 3"
b1011110101000010111000011110110 2"
bx 1"
00"
b11011100111000010100001010111101 ,"
0+"
0*"
0)"
b0 ("
b0 '"
1""
b10111001110000101000010101111010 !"
b1011110101000010111000011101110 ~
bx }
0|
b11001100111000010100001010111101 x
0w
0v
0u
b0 t
b0 s
1n
b10011001110000101000010101111010 m
b1011110101000010111000011100110 l
bx k
0j
b10111100111000010100001010111101 f
0e
0d
0c
b0 b
b0 a
1\
b1111001110000101000010101111010 [
b1011110101000010111000011011110 Z
bx Y
0X
b10101100111000010100001010111101 T
0S
0R
0Q
b0 P
b0 O
1J
b1011001110000101000010101111010 I
b1011110101000010111000011010110 H
bx G
0F
b0 B
b0 A
b0 @
b0 ?
b0 >
b0 4
b0 3
b0 2
b0 1
00
1/
bx .
bx -
bx ,
0+
bx *
b100000000000000000000000000000 )
b11100000000000000000000000000000 (
0'
x&
0%
b0 $
0#
0"
b0 !
$end
#5000
1%
#10000
0%
#15000
b1 $
b1 >
1%
1'
#20000
0%
#25000
1F
1X
1j
1|
10"
1B"
b1 @
1%
1+
b100000000000000000000000000000 *
b100000000000000000000000000000 .
b100000000000000000000000000000 G
b100000000000000000000000000000 Y
b100000000000000000000000000000 k
b100000000000000000000000000000 }
b100000000000000000000000000000 1"
b100000000000000000000000000000 C"
#30000
0%
#35000
0J
b11011010111111001010110001001100 I
b10011001010110011111101110110 H
0\
b10011010111111001010110001001100 [
b10011001010110011111101100110 Z
0n
b1011010111111001010110001001100 m
b10011001010110011111100010110 l
0""
b11010111111001010110001001100 !"
b10011001010110011111100000110 ~
04"
b11011010111111001010110001001100 3"
b10011001010110011111100110110 2"
0F"
b10011010111111001010110001001100 E"
b10011001010110011111100100110 D"
b1111110101000010111000011010110 O
b11101101011111100101011000100110 T
b1111110101000010111000011011110 a
b11001101011111100101011000100110 f
b1111110101000010111000011100110 s
b101101011111100101011000100110 x
b1111110101000010111000011101110 '"
b1101011111100101011000100110 ,"
b1111110101000010111000011110110 9"
b1101101011111100101011000100110 >"
b1111110101000010111000011111110 K"
b1001101011111100101011000100110 P"
b100000000 $
b100000000 >
b1 A
1%
0+
#40000
0%
#45000
b110101111110010101100010011000 E"
b100110010101100111111001001101 D"
b10110101111110010101100010011000 3"
b100110010101100111111001101101 2"
b110101111110010101100010011000 !"
b100110010101100111111000001101 ~
b10110101111110010101100010011000 m
b100110010101100111111000101101 l
b110101111110010101100010011000 [
b100110010101100111111001001101 Z
10
b110 W"
b110 X"
b110 Y"
b0 V"
b10110101111110010101100010011000 I
b100110010101100111111001101101 H
b100000001 $
b100000001 >
b10 A
b1 L"
1O"
1N"
b1011110101000010111000011111110 K"
b10011010111111001010110001001100 P"
b1 :"
1="
1<"
b1011110101000010111000011110110 9"
b11011010111111001010110001001100 >"
b1 ("
1+"
1*"
b1011110101000010111000011101110 '"
b11010111111001010110001001100 ,"
b1 t
1w
1v
b1011110101000010111000011100110 s
b1011010111111001010110001001100 x
b1 b
1e
1d
b1011110101000010111000011011110 a
b10011010111111001010110001001100 f
b10000000000000000000000000000000100000000000000000000000000000001000000000000000000000000000000010000000000000000000000000000000100000000000000000000000000000001 4
b10000000000000000000000000000000100000000000000000000000000000001000000000000000000000000000000010000000000000000000000000000000100000000000000000000000000000001 Q"
b1 P
b111111 1
b111111 R"
1S
b111111 2
1R
b1011110101000010111000011010110 O
b11011010111111001010110001001100 T
1%
#50000
0%
#55000
b1101011111100101011000100110000 I
b1001100001011000111110011011010 H
b1101011111100101011000100110000 [
b1001100001011000111110010011010 Z
b1101011111100101011000100110000 m
b1001100001011000111110011011010 l
b1101011111100101011000100110000 !"
b1001100001011000111110010011010 ~
b1101011111100101011000100110000 3"
b1001100001011000111110011011010 2"
b110 Y"
b1100 W"
b110 X"
b1101011111100101011000100110000 E"
b1001100001011000111110010011010 D"
b10 P
b111110101000010111000011010110 O
b10110101111110010101100010011000 T
b10 b
b111110101000010111000011011110 a
b110101111110010101100010011000 f
b10 t
b111110101000010111000011100110 s
b10110101111110010101100010011000 x
b10 ("
b111110101000010111000011101110 '"
b110101111110010101100010011000 ,"
b10 :"
b111110101000010111000011110110 9"
b10110101111110010101100010011000 >"
b100000000000000000000000000000001000000000000000000000000000000010000000000000000000000000000000100000000000000000000000000000001000000000000000000000000000000010 4
b100000000000000000000000000000001000000000000000000000000000000010000000000000000000000000000000100000000000000000000000000000001000000000000000000000000000000010 Q"
b10 L"
b111110101000010111000011111110 K"
b110101111110010101100010011000 P"
b100000010 $
b100000010 >
b11 A
1%
#60000
0%
#65000
b11010111111001010110001001100000 E"
b11000010110001111100100110101 D"
b11010111111001010110001001100000 3"
b11000010110001111100100110101 2"
b11010111111001010110001001100000 !"
b11000010110001111100100110101 ~
b11010111111001010110001001100000 m
b11000010110001111100100110101 l
b11010111111001010110001001100000 [
b11000010110001111100100110101 Z
b110 Y"
b10010 W"
b110 X"
b11010111111001010110001001100000 I
b11000010110001111100100110101 H
b100000011 $
b100000011 >
b100 A
b11 L"
b11110101000010111000011111110 K"
b1101011111100101011000100110000 P"
b11 :"
b11110101000010111000011110110 9"
b1101011111100101011000100110000 >"
b11 ("
b11110101000010111000011101110 '"
b1101011111100101011000100110000 ,"
b11 t
b11110101000010111000011100110 s
b1101011111100101011000100110000 x
b11 b
b11110101000010111000011011110 a
b1101011111100101011000100110000 f
b110000000000000000000000000000001100000000000000000000000000000011000000000000000000000000000000110000000000000000000000000000001100000000000000000000000000000011 4
b110000000000000000000000000000001100000000000000000000000000000011000000000000000000000000000000110000000000000000000000000000001100000000000000000000000000000011 Q"
b11 P
b11110101000010111000011010110 O
b1101011111100101011000100110000 T
1%
#70000
0%
#75000
b10101111110010101100010011000000 I
b110000001100010111001011101011 H
b10101111110010101100010011000000 [
b110000001100010111001011101011 Z
b10101111110010101100010011000000 m
b110000001100010111001011101011 l
b10101111110010101100010011000000 !"
b110000001100010111001011101011 ~
b10101111110010101100010011000000 3"
b110000001100010111001011101011 2"
b10101111110010101100010011000000 E"
b110000001100010111001011101011 D"
0R
b1010110111110100110101000001011 O
b11010111111001010110001001100000 T
0d
b1010110111110100110101000010011 a
b11010111111001010110001001100000 f
0v
b1010110111110100110101000011011 s
b11010111111001010110001001100000 x
0*"
b1010110111110100110101000100011 '"
b11010111111001010110001001100000 ,"
0<"
b1010110111110100110101000101011 9"
b11010111111001010110001001100000 >"
b0 2
0N"
b1010110111110100110101000110011 K"
b11010111111001010110001001100000 P"
0F
0X
0j
0|
00"
0B"
b10 @
b100000100 $
b100000100 >
b101 A
1%
#80000
0%
#85000
b11 $
b11 >
b11 @
b10010 !
b10010 B
1%
#90000
0%
#95000
b0 @
b11111111100000001 $
b11111111100000001 >
1"
1#
1%
#96000
b11100000000000000000000000000000 *
b11100000000000000000000000000000 .
b11100000000000000000000000000000 G
b11100000000000000000000000000000 Y
b11100000000000000000000000000000 k
b11100000000000000000000000000000 }
b11100000000000000000000000000000 1"
b11100000000000000000000000000000 C"
#100000
0%
#105000
b1 $
b1 >
0"
1%
#110000
0%
#115000
1%
#116000
1+
#120000
0%
#125000
b0 A
1F
1X
1j
1|
10"
1B"
b1 @
1%
#126000
0+
#130000
0%
#135000
b1011111100101011000100110000000 I
b1100000011000100110010101010111 H
b1011111100101011000100110000000 [
b1100000011000100110010101010111 Z
b1011111100101011000100110000000 m
b1100000011000100110010101010111 l
b1011111100101011000100110000000 !"
b1100000011000100110010101010111 ~
b1011111100101011000100110000000 3"
b1100000011000100110010101010111 2"
b110 Y"
b11000 W"
b110 X"
b1011111100101011000100110000000 E"
b1100000011000100110010101010111 D"
b100 P
1R
b110110111110100110101000001011 O
b10101111110010101100010011000000 T
b100 b
1d
b110110111110100110101000010011 a
b10101111110010101100010011000000 f
b100 t
1v
b110110111110100110101000011011 s
b10101111110010101100010011000000 x
b100 ("
1*"
b110110111110100110101000100011 '"
b10101111110010101100010011000000 ,"
b100 :"
1<"
b110110111110100110101000101011 9"
b10101111110010101100010011000000 >"
b1000000000000000000000000000000010000000000000000000000000000000100000000000000000000000000000001000000000000000000000000000000010000000000000000000000000000000100 4
b1000000000000000000000000000000010000000000000000000000000000000100000000000000000000000000000001000000000000000000000000000000010000000000000000000000000000000100 Q"
b100 L"
b111111 2
1N"
b110110111110100110101000110011 K"
b10101111110010101100010011000000 P"
b100000000 $
b100000000 >
b1 A
1%
#140000
0%
#145000
b10111111001010110001001100000000 E"
b1000000010001001100101010101111 D"
b10111111001010110001001100000000 3"
b1000000010001001100101010101111 2"
b10111111001010110001001100000000 !"
b1000000010001001100101010101111 ~
b10111111001010110001001100000000 m
b1000000010001001100101010101111 l
b10111111001010110001001100000000 [
b1000000010001001100101010101111 Z
b110 Y"
b11110 W"
b110 X"
b10111111001010110001001100000000 I
b1000000010001001100101010101111 H
b100000001 $
b100000001 >
b10 A
b101 L"
b10110111110100110101000110011 K"
b1011111100101011000100110000000 P"
b101 :"
b10110111110100110101000101011 9"
b1011111100101011000100110000000 >"
b101 ("
b10110111110100110101000100011 '"
b1011111100101011000100110000000 ,"
b101 t
b10110111110100110101000011011 s
b1011111100101011000100110000000 x
b101 b
b10110111110100110101000010011 a
b1011111100101011000100110000000 f
b1010000000000000000000000000000010100000000000000000000000000000101000000000000000000000000000001010000000000000000000000000000010100000000000000000000000000000101 4
b1010000000000000000000000000000010100000000000000000000000000000101000000000000000000000000000001010000000000000000000000000000010100000000000000000000000000000101 Q"
b101 P
b10110111110100110101000001011 O
b1011111100101011000100110000000 T
1%
#150000
0%
#155000
b1111110010101100010011000000000 I
b10011001010111011111 H
b1111110010101100010011000000000 [
b10011001010111011111 Z
b1111110010101100010011000000000 m
b10011001010111011111 l
b1111110010101100010011000000000 !"
b10011001010111011111 ~
b1111110010101100010011000000000 3"
b10011001010111011111 2"
b1111110010101100010011000000000 E"
b10011001010111011111 D"
0R
b110111001111110011010010111010 O
b10111111001010110001001100000000 T
0d
b110111001111110011010011000010 a
b10111111001010110001001100000000 f
0v
b110111001111110011010011001010 s
b10111111001010110001001100000000 x
0*"
b110111001111110011010011010010 '"
b10111111001010110001001100000000 ,"
0<"
b110111001111110011010011011010 9"
b10111111001010110001001100000000 >"
b0 2
0N"
b110111001111110011010011100010 K"
b10111111001010110001001100000000 P"
b100000010 $
b100000010 >
b11 A
1%
#160000
0%
